cex/__init__.py
cex/client.py
cex/const.py
cex/test.py
cexapi-0.0.2.dist-info/DESCRIPTION.rst
cexapi-0.0.2.dist-info/METADATA
cexapi-0.0.2.dist-info/RECORD
cexapi-0.0.2.dist-info/WHEEL
cexapi-0.0.2.dist-info/metadata.json
cexapi-0.0.2.dist-info/top_level.txt
